{"path":".","children":[{"path":"./8ch_v5_nosma","name":"8ch_v5_nosma","children":[{"path":"./8ch_v5_nosma/8ch_v5_nosma-cache.lib","name":"8ch_v5_nosma-cache.lib"},{"path":"./8ch_v5_nosma/8ch_v5_nosma.kicad_pcb","name":"8ch_v5_nosma.kicad_pcb"},{"path":"./8ch_v5_nosma/8ch_v5_nosma.sch","name":"8ch_v5_nosma.sch"},{"path":"./8ch_v5_nosma/8ch_v5_nosma_stdsma.kicad_pcb","name":"8ch_v5_nosma_stdsma.kicad_pcb"},{"path":"./8ch_v5_nosma/channel.sch","name":"channel.sch"},{"path":"./8ch_v5_nosma/dac_AD5675-cache.lib","name":"dac_AD5675-cache.lib"},{"path":"./8ch_v5_nosma/dac_AD5675.sch","name":"dac_AD5675.sch"},{"path":"./8ch_v5_nosma/dac_proto","name":"dac_proto","children":[{"path":"./8ch_v5_nosma/dac_proto/channel.sch","name":"channel.sch"},{"path":"./8ch_v5_nosma/dac_proto/channel_v2.sch","name":"channel_v2.sch"},{"path":"./8ch_v5_nosma/dac_proto/dac_proto-cache.lib","name":"dac_proto-cache.lib"},{"path":"./8ch_v5_nosma/dac_proto/dac_proto.kicad_pcb","name":"dac_proto.kicad_pcb"},{"path":"./8ch_v5_nosma/dac_proto/dac_proto.sch","name":"dac_proto.sch"},{"path":"./8ch_v5_nosma/dac_proto/temp.sch","name":"temp.sch"}]},{"path":"./8ch_v5_nosma/power2.sch","name":"power2.sch"},{"path":"./8ch_v5_nosma/relay_test.sch","name":"relay_test.sch"}]},{"path":"./back_panel","name":"back_panel","children":[{"path":"./back_panel/back_panel-cache.lib","name":"back_panel-cache.lib"},{"path":"./back_panel/back_panel.kicad_pcb","name":"back_panel.kicad_pcb"},{"path":"./back_panel/back_panel.sch","name":"back_panel.sch"}]},{"path":"./back_v2","name":"back_v2","children":[{"path":"./back_v2/back_v2-cache.lib","name":"back_v2-cache.lib"},{"path":"./back_v2/back_v2.kicad_pcb","name":"back_v2.kicad_pcb"},{"path":"./back_v2/back_v2.sch","name":"back_v2.sch"}]},{"path":"./back_v3","name":"back_v3","children":[{"path":"./back_v3/back_v3-cache.lib","name":"back_v3-cache.lib"},{"path":"./back_v3/back_v3.kicad_pcb","name":"back_v3.kicad_pcb"},{"path":"./back_v3/back_v3.sch","name":"back_v3.sch"}]},{"path":"./back_v4","name":"back_v4","children":[{"path":"./back_v4/back_v4-cache.lib","name":"back_v4-cache.lib"},{"path":"./back_v4/back_v4.kicad_pcb","name":"back_v4.kicad_pcb"},{"path":"./back_v4/back_v4.sch","name":"back_v4.sch"}]},{"path":"./front_panel","name":"front_panel","children":[{"path":"./front_panel/back_panel.kicad_pcb","name":"back_panel.kicad_pcb"},{"path":"./front_panel/front_panel-cache.lib","name":"front_panel-cache.lib"},{"path":"./front_panel/front_panel.kicad_pcb","name":"front_panel.kicad_pcb"},{"path":"./front_panel/front_panel.sch","name":"front_panel.sch"}]},{"path":"./pmos_board","name":"pmos_board","children":[{"path":"./pmos_board/coax_ch.sch","name":"coax_ch.sch"},{"path":"./pmos_board/pmos_board-cache.lib","name":"pmos_board-cache.lib"},{"path":"./pmos_board/pmos_board-rescue.lib","name":"pmos_board-rescue.lib"},{"path":"./pmos_board/pmos_board.kicad_pcb","name":"pmos_board.kicad_pcb"},{"path":"./pmos_board/pmos_board.sch","name":"pmos_board.sch"},{"path":"./pmos_board/temp.sch","name":"temp.sch"}]},{"path":"./power_supply","name":"power_supply","children":[{"path":"./power_supply/power_cui-cache.lib","name":"power_cui-cache.lib"},{"path":"./power_supply/power_cui.kicad_pcb","name":"power_cui.kicad_pcb"},{"path":"./power_supply/power_cui.sch","name":"power_cui.sch"}]},{"path":"./supercap","name":"supercap","children":[{"path":"./supercap/supercap-cache.lib","name":"supercap-cache.lib"},{"path":"./supercap/supercap.kicad_pcb","name":"supercap.kicad_pcb"},{"path":"./supercap/supercap.sch","name":"supercap.sch"}]},{"path":"./switch_board","name":"switch_board","children":[{"path":"./switch_board/i2c.sch","name":"i2c.sch"},{"path":"./switch_board/relay.sch","name":"relay.sch"},{"path":"./switch_board/switch_board-cache.lib","name":"switch_board-cache.lib"},{"path":"./switch_board/switch_board.kicad_pcb","name":"switch_board.kicad_pcb"},{"path":"./switch_board/switch_board.sch","name":"switch_board.sch"}]}]}